mosyle/__init__.py
mosyle/__main__.py
mosyle/__version__.py
mosyle/accounts.py
mosyle/actions.py
mosyle/app.py
mosyle/cisco_ise.py
mosyle/classes.py
mosyle/devices.py
mosyle/str_enum.py
mosyle/users.py
mosyle/api/__init__.py
mosyle/api/account_operation.py
mosyle/api/cisco_ise_operation.py
mosyle/api/class_column.py
mosyle/api/class_operation.py
mosyle/api/class_platform.py
mosyle/api/device_column.py
mosyle/api/device_lost_mode_operation.py
mosyle/api/device_operation.py
mosyle/api/device_platform.py
mosyle/api/user_column.py
mosyle/api/user_list_type.py
mosyle/api/user_operation.py
mosyle/api/user_operation_type.py
sample/simple.py
mosyle-0.0.7.dist-info/METADATA
mosyle-0.0.7.dist-info/WHEEL
mosyle-0.0.7.dist-info/entry_points.txt
mosyle-0.0.7.dist-info/top_level.txt
mosyle-0.0.7.dist-info/RECORD
