Metadata-Version: 2.1
Name: mosyle
Version: 0.0.7
Summary: Mosyle Manager Python API
Author-email: Nathan McGuire <mcguiren@osageschools.org>
Maintainer-email: Nathan McGuire <mcguiren@osageschools.org>
Project-URL: Github, https://github.com/SchoolOfTheOsage/mosyle
Project-URL: Bug Reports, https://github.com/SchoolOfTheOsage/mosyle/issues
Project-URL: Source, https://github.com/SchoolOfTheOsage/mosyle
Keywords: python,api,apple,mdm,mosyle
Classifier: Development Status :: 1 - Planning
Classifier: Intended Audience :: System Administrators
Classifier: License :: OSI Approved :: MIT License
Classifier: Programming Language :: Python :: 3
Classifier: Programming Language :: Python :: 3.7
Classifier: Programming Language :: Python :: 3.8
Classifier: Programming Language :: Python :: 3.9
Classifier: Programming Language :: Python :: 3.10
Classifier: Programming Language :: Python :: 3.11
Classifier: Programming Language :: Python :: 3 :: Only
Requires-Python: >=3.7
Requires-Dist: requests
Requires-Dist: importlib-metadata ; python_version < "3.8"
Provides-Extra: dev
Requires-Dist: check-manifest ; extra == 'dev'
Provides-Extra: test
Requires-Dist: coverage ; extra == 'test'
